pl_intelligence/__init__.py
pl_intelligence/tools/__init__.py
pl_intelligence/tools/pl_intelligence_tool.py
pl_intelligence/tools/utils.py
pl_intelligence/yamls/pl_intelligence_tool.yaml
tests/__init__.py
tests/test_pl_intelligence_tool.py
pl_intelligence-0.0.1.dist-info/METADATA
pl_intelligence-0.0.1.dist-info/WHEEL
pl_intelligence-0.0.1.dist-info/entry_points.txt
pl_intelligence-0.0.1.dist-info/top_level.txt
pl_intelligence-0.0.1.dist-info/RECORD
