Metadata-Version: 2.1
Name: pl_intelligence
Version: 0.0.1
Summary: This is importing place intelligence flow
